fast_map/__init__.py
fast_map/fast_map.py
fast_map/fast_map_async.py
fast_map-0.2.0.dist-info/LICENSE
fast_map-0.2.0.dist-info/METADATA
fast_map-0.2.0.dist-info/WHEEL
fast_map-0.2.0.dist-info/top_level.txt
fast_map-0.2.0.dist-info/RECORD
