Metadata-Version: 2.1
Name: fast-map
Version: 0.2.0
Summary: Combines multiprocessing and multithreading for fast computation.
Home-page: https://github.com/michalmonday/fast_map
Author: Michal Borowski
Author-email: michalmonday17@gmail.com
Project-URL: Bug Tracker, https://github.com/michalmonday/fast_map/issues
Classifier: Programming Language :: Python :: 3
Classifier: License :: OSI Approved :: MIT License
Classifier: Operating System :: OS Independent
Requires-Python: >=3.6
License-File: LICENSE
